codac/__init__.py
codac/codac2.cpython-39-darwin.so
codac/core.cpython-39-darwin.so
codac/empty.cpython-39-darwin.so
codac/unsupported.cpython-39-darwin.so
codac/version.py
codac/tests/__init__.py
codac/tests/test_actions.py
codac/tests/test_arithmetic.py
codac/tests/test_cn.py
codac/tests/test_ctcbox.py
codac/tests/test_ctccartprod.py
codac/tests/test_ctccn.py
codac/tests/test_ctcconstell.py
codac/tests/test_ctcdelay.py
codac/tests/test_ctceval.py
codac/tests/test_ctcstatic.py
codac/tests/test_definition.py
codac/tests/test_function.py
codac/tests/test_multi_arithmetic.py
codac/tests/test_numpy.py
codac/tests/test_sepbox.py
codac-1.5.7.dist-info/METADATA
codac-1.5.7.dist-info/WHEEL
codac-1.5.7.dist-info/top_level.txt
codac-1.5.7.dist-info/RECORD
