Metadata-Version: 2.2
Name: codac
Version: 1.5.7
Summary: Codac is a library providing tools for constraint programming over reals and trajectories.
Home-page: http://codac.io
Author: Simon Rohou, Benoit Desrochers
Author-email: simon.rohou@ensta-bretagne.fr
License: LGPLv3+
Classifier: Development Status :: 3 - Alpha
Classifier: Topic :: Scientific/Engineering :: Mathematics
Classifier: License :: OSI Approved :: GNU Lesser General Public License v3 or later (LGPLv3+)
Requires-Dist: pip>=19.0.0
Requires-Dist: vibes
Dynamic: author
Dynamic: author-email
Dynamic: classifier
Dynamic: description
Dynamic: home-page
Dynamic: license
Dynamic: requires-dist
Dynamic: summary
